soma/__init__.py
soma/estilo/__init__.py
soma/estilo/datasets.py
soma/estilo/modelling.py
soma/estilo/utils.py
soma-0.1.33.dist-info/METADATA
soma-0.1.33.dist-info/WHEEL
soma-0.1.33.dist-info/top_level.txt
soma-0.1.33.dist-info/RECORD
